{"web":{"client_id":"687797313120-n9mpc3d1fj9ecr59omtjt84l0jkalqlh.apps.googleusercontent.com","project_id":"pooja-160019","auth_uri":"https://accounts.google.com/o/oauth2/auth","token_uri":"https://accounts.google.com/o/oauth2/token","auth_provider_x509_cert_url":"https://www.googleapis.com/oauth2/v1/certs","client_secret":"qEFl3MqXrPbvc1BoEaKCy75P","redirect_uris":["http://ec2-107-21-71-71.compute-1.amazonaws.com/ouath2callback"],"javascript_origins":["http://107.21.71.71","http://localhost:5000","http://0.0.0.0:5000","http://ec2-107-21-71-71.compute-1.amazonaws.com"]}}